algorithms/__init__.py
data_structures/__init__.py
python_ds-1.0.0.dist-info/LICENSE
python_ds-1.0.0.dist-info/METADATA
python_ds-1.0.0.dist-info/WHEEL
python_ds-1.0.0.dist-info/top_level.txt
python_ds-1.0.0.dist-info/RECORD
