Metadata-Version: 2.1
Name: python-ds
Version: 1.0.0
Summary: No non-sense solutions to common Data Structure and Algorithm interview questions in Python.
Home-page: https://github.com/prabhupant/python-ds
Author: parth parikh
Author-email: subzero23@sudomail.com
License: UNKNOWN
Platform: UNKNOWN
Classifier: Programming Language :: Python :: 3
Classifier: License :: OSI Approved :: MIT License
Classifier: Operating System :: OS Independent
License-File: LICENSE
